[
  {
    "date": "2026-05-10",
    "title": "Youth Camp \"AWAKE\" Successfully Held",
    "category": "Event",
    "description": "Hosted a 3-day youth camp with over 60 attendees, featuring worship nights, workshops, and small-group discipleship."
  },
  {
    "date": "2026-03-02",
    "title": "Outreach Feeding Program",
    "category": "Outreach",
    "description": "Partnered with the church's mission team to serve meals and share the gospel with 3 nearby communities."
  },
  {
    "date": "2026-01-18",
    "title": "New Officers Installed",
    "category": "Leadership",
    "description": "Installed the current set of officers for the new term in a special Sunday service."
  }
]
